undefined/__init__.py
undefined/mypy.py
typed_undefined-0.1.0.dist-info/LICENSE
typed_undefined-0.1.0.dist-info/WHEEL
typed_undefined-0.1.0.dist-info/METADATA
typed_undefined-0.1.0.dist-info/RECORD
